fastapi_orm_helper/__init__.py
fastapi_orm_helper/base_repository.py
fastapi_orm_helper/dependencies/pagination.py
fastapi_orm_helper/entity_mappers/entity_mapper.py
fastapi_orm_helper/entity_mappers/entity_reverse_mapper.py
fastapi_orm_helper/enums/join_type_enum.py
fastapi_orm_helper/helpers/deep_pluck.py
fastapi_orm_helper/helpers/get_db_session.py
fastapi_orm_helper/helpers/join.py
fastapi_orm_helper-0.1.7.dist-info/METADATA
fastapi_orm_helper-0.1.7.dist-info/WHEEL
fastapi_orm_helper-0.1.7.dist-info/licenses/LICENSE
fastapi_orm_helper-0.1.7.dist-info/RECORD
