Metadata-Version: 2.4
Name: fastapi_orm_helper
Version: 0.1.7
Summary: FastAPI ORM Helper
Project-URL: Homepage, https://github.com/megatron-global/fastapi-orm-helper
Project-URL: Bug Tracker, https://github.com/megatron-global/fastapi-orm-helper/issues
Author-email: Dzung Nguyen <dung@megatron-solutions.com>
License-File: LICENSE
Classifier: License :: OSI Approved :: MIT License
Classifier: Operating System :: OS Independent
Classifier: Programming Language :: Python :: 3
Requires-Python: >=3.10
